{
  "id": 318,
  "name": "carvanha",
  "types": [
    "water",
    "dark"
  ],
  "sprites": {
    "official": {
      "default": "https://raw.githubusercontent.com/PokeAPI/sprites/master/sprites/pokemon/other/official-artwork/318.png"
    },
    "home": {
      "default": "https://raw.githubusercontent.com/PokeAPI/sprites/master/sprites/pokemon/other/home/318.png",
      "shiny": "https://raw.githubusercontent.com/PokeAPI/sprites/master/sprites/pokemon/other/home/shiny/318.png"
    },
    "default": {
      "default": "https://raw.githubusercontent.com/PokeAPI/sprites/master/sprites/pokemon/318.png",
      "shiny": "https://raw.githubusercontent.com/PokeAPI/sprites/master/sprites/pokemon/shiny/318.png"
    },
    "variants": {
      "carvanha": {
        "default": "https://raw.githubusercontent.com/PokeAPI/sprites/master/sprites/pokemon/318.png",
        "shiny": "https://raw.githubusercontent.com/PokeAPI/sprites/master/sprites/pokemon/shiny/318.png"
      }
    }
  },
  "abilities": [
    {
      "name": "rough-skin",
      "description": "Hurts to touch."
    },
    {
      "name": "speed-boost",
      "description": "Gradually boosts SPEED."
    }
  ],
  "description": "CARVANHA’s strongly developed jaws\nand its sharply pointed fangs pack the\ndestructive power to rip out boat hulls.\fMany boats have been attacked and\nsunk by this POKéMON."
}