{
  "id": 703,
  "name": "carbink",
  "types": [
    "rock",
    "fairy"
  ],
  "sprites": {
    "official": {
      "default": "https://raw.githubusercontent.com/PokeAPI/sprites/master/sprites/pokemon/other/official-artwork/703.png"
    },
    "home": {
      "default": "https://raw.githubusercontent.com/PokeAPI/sprites/master/sprites/pokemon/other/home/703.png",
      "shiny": "https://raw.githubusercontent.com/PokeAPI/sprites/master/sprites/pokemon/other/home/shiny/703.png"
    },
    "default": {
      "default": "https://raw.githubusercontent.com/PokeAPI/sprites/master/sprites/pokemon/703.png",
      "shiny": "https://raw.githubusercontent.com/PokeAPI/sprites/master/sprites/pokemon/shiny/703.png"
    },
    "variants": {
      "carbink": {
        "default": "https://raw.githubusercontent.com/PokeAPI/sprites/master/sprites/pokemon/703.png",
        "shiny": "https://raw.githubusercontent.com/PokeAPI/sprites/master/sprites/pokemon/shiny/703.png"
      }
    }
  },
  "abilities": [
    {
      "name": "clear-body",
      "description": "Prevents ability reduction."
    },
    {
      "name": "sturdy",
      "description": "Negates 1-hit KO attacks."
    }
  ],
  "description": "Born from the temperatures and pressures\ndeep underground, it fires beams from the\nstone in its head."
}